odin/__init__.py
odin/chores.py
odin/cleanup.py
odin/core.py
odin/dag.py
odin/executor.py
odin/generate.py
odin/k8s.py
odin/serve.py
odin/status.py
odin/store.py
odin/version.py
odin/addons/__init__.py
odin/addons/demo_chore_addon.py
odin/addons/mead_eval_slack.py
odin/handlers/__init__.py
odin/handlers/deployment.py
odin/handlers/elasticjob.py
odin/handlers/job.py
odin/handlers/mpijob.py
odin/handlers/pod.py
odin/handlers/pytorchjob.py
odin/handlers/service.py
odin/handlers/tfjob.py
odin/model/__init__.py
odin/model/selector.py
odin/mongo/__init__.py
odin/mongo/store.py
odin/postgres/__init__.py
odin/postgres/store.py
odin/utils/__init__.py
odin/utils/auth.py
odin/utils/hash.py
odin/utils/render.py
odin/utils/yaml_utils.py
odin_ml-0.7.6.dist-info/LICENSE
odin_ml-0.7.6.dist-info/METADATA
odin_ml-0.7.6.dist-info/NOTICE
odin_ml-0.7.6.dist-info/WHEEL
odin_ml-0.7.6.dist-info/entry_points.txt
odin_ml-0.7.6.dist-info/top_level.txt
odin_ml-0.7.6.dist-info/RECORD
