Metadata-Version: 2.1
Name: odin-ml
Version: 0.7.6
Summary: UNKNOWN
Home-page: UNKNOWN
License: UNKNOWN
Platform: UNKNOWN
License-File: ../../LICENSE
License-File: ../../NOTICE
Requires-Dist: numpy
Requires-Dist: pyyaml (>=5.1)
Requires-Dist: websockets
Requires-Dist: kubernetes
Requires-Dist: shortid
Requires-Dist: GitPython
Requires-Dist: pymongo (<=3.12.0)
Requires-Dist: SQLAlchemy
Requires-Dist: psycopg2-binary
Requires-Dist: ruamel.yaml
Requires-Dist: cachetools
Requires-Dist: prompt-toolkit (>=2.0.0)
Requires-Dist: requests-async
Requires-Dist: requests
Requires-Dist: pandas
Requires-Dist: mead-baseline (>=2.0.1)
Requires-Dist: mead-xpctl-client
Provides-Extra: test
Requires-Dist: pytest ; extra == 'test'
